{
  "session": 433,
  "title": "Atlas Expansion XIV: Domains 806-835 (Representation Theory & K-Theory)",
  "eml_operator": "eml(x,y) = exp(x) - ln(y)",
  "analysis": {
    "model": "AtlasExpansion14EML",
    "representation_theory": {
      "object": "EML classification: Representation theory domains 806-820",
      "D806": {
        "name": "Representation theory of finite groups",
        "depth": "EML-0",
        "reason": "Character tables; finite group algebra = EML-0"
      },
      "D807": {
        "name": "Representation theory of Lie groups",
        "depth": "EML-3",
        "reason": "Weyl character formula; complex representations = EML-3"
      },
      "D808": {
        "name": "Representation theory of Lie algebras",
        "depth": "EML-3",
        "reason": "Highest weight modules; Verma modules = EML-3"
      },
      "D809": {
        "name": "Geometric Langlands program",
        "depth": "EML-3",
        "reason": "D-modules on Bun_G; perverse sheaves = EML-3"
      },
      "D810": {
        "name": "Kazhdan-Lusztig theory",
        "depth": "EML-3",
        "reason": "KL polynomials; Hecke algebra = EML-3"
      },
      "D811": {
        "name": "Perverse sheaves (BBD)",
        "depth": "EML-3",
        "reason": "Intersection cohomology; complex = EML-3"
      },
      "D812": {
        "name": "Category O (BGG)",
        "depth": "EML-3",
        "reason": "Verma modules; highest weight category = EML-3"
      },
      "D813": {
        "name": "Geometric representation theory (Nakajima)",
        "depth": "EML-3",
        "reason": "Quiver varieties; complex algebraic = EML-3"
      },
      "D814": {
        "name": "Metaplectic representations (Weil)",
        "depth": "EML-3",
        "reason": "Theta correspondence; complex oscillatory = EML-3"
      },
      "D815": {
        "name": "Admissible representations of p-adic groups",
        "depth": "EML-3",
        "reason": "Smooth GL_n(F_p): complex Hecke = EML-3"
      },
      "D816": {
        "name": "Local Langlands correspondence",
        "depth": "EML-3",
        "reason": "\u03c0 \u2194 \u03c6: complex Weil-Deligne = EML-3"
      },
      "D817": {
        "name": "p-adic representation theory",
        "depth": "EML-3",
        "reason": "(\u03c6,\u0393)-modules; p-adic Hodge = EML-3"
      },
      "D818": {
        "name": "Modular representation theory (char p)",
        "depth": "EML-\u221e",
        "reason": "Decomposition numbers; non-constructive in general = EML-\u221e"
      },
      "D819": {
        "name": "Categorification (Khovanov-Lauda-Rouquier)",
        "depth": "EML-3",
        "reason": "2-categorification of quantum groups = EML-3"
      },
      "D820": {
        "name": "Tensor categories and fusion categories",
        "depth": "EML-3",
        "reason": "F-matrices; modular tensor categories = EML-3"
      }
    },
    "k_theory": {
      "object": "EML classification: K-theory and motivic cohomology domains 821-835",
      "D821": {
        "name": "Algebraic K-theory K_n(R)",
        "depth": "EML-3",
        "reason": "Higher K-groups via BGL\u207a; complex homotopy = EML-3"
      },
      "D822": {
        "name": "Milnor K-theory K^M_n(F)",
        "depth": "EML-0",
        "reason": "Tensor product of F\u00d7/(2): algebraic = EML-0"
      },
      "D823": {
        "name": "Motivic cohomology H^{p,q}(X,Z)",
        "depth": "EML-3",
        "reason": "Algebraic cycles modulo equivalence; complex = EML-3"
      },
      "D824": {
        "name": "Bloch-Kato conjecture (Voevodsky)",
        "depth": "EML-3",
        "reason": "Norm residue map K^M \u2192 H^n_et: complex = EML-3"
      },
      "D825": {
        "name": "Algebraic cycles (Chow groups)",
        "depth": "EML-\u221e",
        "reason": "Homological \u2260 algebraic equivalence; non-constructive = EML-\u221e"
      },
      "D826": {
        "name": "Regulator maps (Borel, Beilinson)",
        "depth": "EML-3",
        "reason": "r: K_n(R) \u2192 Deligne cohomology = EML-3"
      },
      "D827": {
        "name": "Motivic integration",
        "depth": "EML-3",
        "reason": "Arc spaces; motivic measure = EML-3"
      },
      "D828": {
        "name": "A\u00b9-homotopy category (Morel-Voevodsky)",
        "depth": "EML-3",
        "reason": "Motivic spheres; complex analogy = EML-3"
      },
      "D829": {
        "name": "Topological Hochschild homology (THH)",
        "depth": "EML-3",
        "reason": "S\u00b9-equivariant; cyclotomic structure = EML-3"
      },
      "D830": {
        "name": "TC (topological cyclic homology)",
        "depth": "EML-3",
        "reason": "p-adic regulator; Nikolaus-Scholze = EML-3"
      },
      "D831": {
        "name": "Perfectoid K-theory",
        "depth": "EML-3",
        "reason": "K(A_inf); tilting equivalence = EML-3"
      },
      "D832": {
        "name": "The K-theory of spaces (Waldhausen)",
        "depth": "EML-3",
        "reason": "A(X) = K(\u03a3\u221e\u03a9\u221eX): spectrum = EML-3"
      },
      "D833": {
        "name": "Equivariant K-theory (Atiyah-Segal)",
        "depth": "EML-3",
        "reason": "K_G(X); representation ring = EML-3"
      },
      "D834": {
        "name": "KK-theory (Kasparov)",
        "depth": "EML-3",
        "reason": "Bivariant K-theory; C*-algebras = EML-3"
      },
      "D835": {
        "name": "Non-commutative geometry (Connes)",
        "depth": "EML-3",
        "reason": "Spectral triple (A,H,D); complex = EML-3"
      }
    },
    "summary": {
      "object": "Depth distribution for domains 806-835",
      "EML_0": [
        "D806 finite group reps",
        "D822 Milnor K-theory"
      ],
      "EML_3": "All other 27 domains: EML-3",
      "EML_inf": [
        "D818 modular rep theory",
        "D825 algebraic cycles"
      ],
      "violations": 0,
      "new_theorem": "T153: Atlas Batch 14 (S433): 30 representation theory/K-theory; total 835"
    },
    "verdicts": {
      "representation": "Lie groups/algebras/Langlands/categorification: EML-3; finite groups: EML-0",
      "k_theory": "K-theory/motivic/THH/TC: all EML-3; Milnor K-theory: EML-0",
      "violations": 0,
      "new_theorem": "T153: Atlas Batch 14"
    }
  },
  "key_theorem": "Atlas Batch 14 (T153, S433): 30 representation theory/K-theory domains. Nearly all EML-3: Lie reps, Geometric Langlands, perverse sheaves, KLR categorification, algebraic K-theory, motivic cohomology, THH, TC, Connes NCG. Only EML-0: finite group reps (character tables) and Milnor K-theory (purely algebraic). EML-\u221e: modular rep theory (decomposition numbers non-constructive) and algebraic cycles. 0 violations. Total domains: 835.",
  "rabbit_hole_log": [
    "Geometric Langlands: EML-3 (D-modules on Bun_G = complex analytic)",
    "THH/TC: EML-3 (cyclotomic structure via Nikolaus-Scholze = complex)",
    "Modular representation theory: EML-\u221e (Lusztig conjectures still open in small char)",
    "Connes NCG: EML-3 (spectral triple \u2014 complex Dirac operator)",
    "NEW: T153 Atlas Batch 14 \u2014 30 domains, 0 violations, total 835"
  ]
}
